twissed/__init__.py
twissed/io/__init__.py
twissed/io/astra.py
twissed/io/fbpic.py
twissed/io/happi.py
twissed/io/smilei.py
twissed/io/tracewin.py
twissed/laser/__init__.py
twissed/laser/laser.py
twissed/launcher/__init__.py
twissed/launcher/launcher.py
twissed/plt/__init__.py
twissed/plt/colormap.py
twissed/plt/matplotlib.py
twissed/plt/rcParams.py
twissed/plt/runs.py
twissed/project/__init__.py
twissed/project/project.py
twissed/step/__init__.py
twissed/step/plotbeam.py
twissed/step/plotfield.py
twissed/step/step.py
twissed/steps/__init__.py
twissed/steps/plotbeam.py
twissed/steps/steps.py
twissed/update_project/__init__.py
twissed/update_project/__main__.py
twissed/update_run/__init__.py
twissed/update_run/__main__.py
twissed/utils/__init__.py
twissed/utils/data.py
twissed/utils/metadata.py
twissed/utils/noweight.py
twissed/utils/physics.py
twissed/utils/stats.py
twissed/utils/tools.py
twissed/utils/units.py
twissed-2.1.1.dist-info/LICENSE
twissed-2.1.1.dist-info/METADATA
twissed-2.1.1.dist-info/WHEEL
twissed-2.1.1.dist-info/top_level.txt
twissed-2.1.1.dist-info/zip-safe
twissed-2.1.1.dist-info/RECORD
