Metadata-Version: 2.1
Name: twissed
Version: 2.1.1
Summary: Python toolbox for LWFA simulations
Home-page: https://github.com/Twissed/Twissed
Author: Damien Minenna
Author-email: damien.minenna@cea.fr
License: MIT
Keywords: Twiss parameters,Beam dynamics,LWFA,PIC
Classifier: Development Status :: 5 - Production/Stable
Classifier: License :: OSI Approved :: MIT License
Classifier: Operating System :: OS Independent
Classifier: Programming Language :: Python :: 3
Classifier: Topic :: Scientific/Engineering :: Physics
Classifier: Typing :: Typed
Requires-Python: >=3.7
License-File: LICENSE
Requires-Dist: numpy
Requires-Dist: pandas
Requires-Dist: scipy
Requires-Dist: h5py
